CREDITS.txt
LICENSE
MANIFEST.in
NEWS.txt
README.rst
ROADMAP.txt
SIMULATED_FUNCTIONS.txt
setup.py
src/android/__init__.py
src/android/toast.py
src/android/ttsspeak.py
src/android/utils/__init__.py
src/android/utils/androidhelper.py
src/android/utils/androidhelper_r6.py
src/android/utils/fix_androidhelper.py
src/sl4a_pydroid_mock_api.egg-info/PKG-INFO
src/sl4a_pydroid_mock_api.egg-info/SOURCES.txt
src/sl4a_pydroid_mock_api.egg-info/dependency_links.txt
src/sl4a_pydroid_mock_api.egg-info/entry_points.txt
src/sl4a_pydroid_mock_api.egg-info/not-zip-safe
src/sl4a_pydroid_mock_api.egg-info/top_level.txt