Metadata-Version: 1.0
Name: sl4a-pydroid-mock-api
Version: 0.4.1
Summary: Simulates the SL4A Python API for Android
Home-page: http://github.com/brousch/sl4a_pydroid_mock_api
Author: Ben Rousch
Author-email: brousch@gmail.com
License: BSD
Keywords: sl4a android api
Platform: UNKNOWN
Classifier: Development Status :: 4 - Beta
Classifier: Environment :: Console
Classifier: Environment :: MacOS X
Classifier: Environment :: Win32 (MS Windows)
Classifier: Intended Audience :: Developers
Classifier: License :: OSI Approved :: BSD License
Classifier: Natural Language :: English
Classifier: Operating System :: MacOS :: MacOS X
Classifier: Operating System :: Microsoft :: Windows
Classifier: Operating System :: POSIX :: Linux
Classifier: Programming Language :: Python :: 2.6
